Metadata-Version: 2.1
Name: love2
Version: 0.0.3
Summary: Code of Love
Author: tiancheng
Author-email: 3277909872@qq.com
